nami/__init__.py
nami/JAX/__init__.py
nami/JAX/function_object.py
nami/TF/__init__.py
nami/TF/function_object.py
nami/Torch/__init__.py
nami/Torch/function_object.py
nami/Torch/functional.py
nami_act-1.1.1.dist-info/LICENSE
nami_act-1.1.1.dist-info/METADATA
nami_act-1.1.1.dist-info/WHEEL
nami_act-1.1.1.dist-info/top_level.txt
nami_act-1.1.1.dist-info/RECORD
