Metadata-Version: 2.1
Name: nami_act
Version: 1.1.1
Summary: Official Repository for Nami: an adaptive self regulatory activation function
Home-page: https://github.com/kandarpa02/Nami.git
Author: Kandarpa Sarkar
Author-email: kandarpaexe@gmail.com
Classifier: Programming Language :: Python :: 3
Classifier: Operating System :: OS Independent
Classifier: Topic :: Scientific/Engineering :: Mathematics
Requires-Python: >=3.8
License-File: LICENSE
